diffReport.py
fuzzyCompare.py
markUp.py
pdfParser.py
diffReport-0.1.4.dist-info/LICENSE
diffReport-0.1.4.dist-info/METADATA
diffReport-0.1.4.dist-info/WHEEL
diffReport-0.1.4.dist-info/top_level.txt
diffReport-0.1.4.dist-info/RECORD
