Metadata-Version: 2.1
Name: diffReport
Version: 0.1.4
Summary: File comparison and report differences
Home-page: https://github.com/vish-nu-ram/diffReport
Author: Vishnuram, Chinky Sharma
Author-email: vishnu.ram@hotmail.com, chinky.sharma@ucdconnect.ie
License: UNKNOWN
Platform: UNKNOWN
Classifier: Programming Language :: Python :: 3
Classifier: Programming Language :: Python :: 3.6
Classifier: Programming Language :: Python :: 3.7
Classifier: License :: OSI Approved :: GNU General Public License v3 or later (GPLv3+)
Classifier: Operating System :: OS Independent
Classifier: Development Status :: 5 - Production/Stable
Classifier: Intended Audience :: Developers
Classifier: Intended Audience :: Financial and Insurance Industry
Classifier: Natural Language :: English
Classifier: Topic :: Text Processing :: Markup :: HTML
License-File: LICENSE
Requires-Dist: fuzzywuzzy
Requires-Dist: pandas
Requires-Dist: pdfminer
